tests/__init__.py
tests/test_conection.py
tests/test_metadata.py
tests/test_utils.py
usebcrp/__init__.py
usebcrp/__version__.py
usebcrp/conection.py
usebcrp/metadata.py
usebcrp/table.py
usebcrp/utils.py
usebcrp-1.0.0.dist-info/LICENSE
usebcrp-1.0.0.dist-info/METADATA
usebcrp-1.0.0.dist-info/WHEEL
usebcrp-1.0.0.dist-info/top_level.txt
usebcrp-1.0.0.dist-info/RECORD
