Metadata-Version: 2.1
Name: usebcrp
Version: 1.0.0
Summary: Python library that consumes the BCRP API, you can query the series and define the time range.
Home-page: https://github.com/MaykolMedrano/usebcrp
Author: Jelsin Palomino & Maykol Medrano
Author-email: maykolmedrano35@gmail.com & jstpalomino@hotmail.com
License: MIT
Keywords: Perú,Peru,BCRP,Banco Central de Reservas del Perú,Series de tiempo
Classifier: Programming Language :: Python
Classifier: Operating System :: Microsoft
Classifier: Intended Audience :: Education
License-File: LICENSE
Requires-Dist: pandas
Requires-Dist: requests
Requires-Dist: tqdm
Requires-Dist: openpyxl
